{"id": 15, "navn": "Grasdekker", "beskrivelse": "Grønne områder som i håndbok R610 (111) benvenes som \"grasplen\" eller \"grasbakke\". Disse områdene er parklike og inngår ikke som en del av kantklipp.", "stedfesting": "LINJE", "objektliste_dato": "2012-05-08", "veiledning": "", "sosinvdbnavn": "Grasdekker_15", "sorteringsnummer": 5220, "kategorier": [{"id": 32, "name": "Miljø - Grønt"}, {"id": 38, "name": "Alle"}, {"id": 104, "name": "Objektlista, alle"}, {"id": 220, "name": "Kommune, standard"}], "egenskapstyper": [{"id": 4129, "navn": "Type", "beskrivelse": "Angir hvilken type vegobjektet er av", "datatype": 30, "datatype_tekst": "FlerverdiAttributt, Tekst", "liste": false, "sensitivitet": 0, "sorteringsnummer": 2, "viktighet": 2, "viktighet_tekst": "PÅKREVD_IKKE_ABSOLUTT", "sosinvdbnavn": "Type_4129", "tillatte_verdier": [{"id": 5090, "kortnavn": "gp", "navn": "Grasplen", "beskrivelse": "Grasplen skal fremstå som en jevn og ensartet kortklipt grasflate, ev. som en del av et prydanlegg. Innslag av mose og ugras skal være minimalt, og ikke virke skjemmende på det visuelle inntrykket. Fra HB 111: \"Grasplen skal binde sammen veg og omgivelser, samt skape grønne områder eller landskapsrom ved å framstå som en jevn og ensartet kortklipt grasflate, eventuelt som er en del av et prydanlegg. Høyden skal være mellom 5 - 12 cm\"", "sorteringsnummer": 1, "objektliste_dato": "2012-05-08"}, {"id": 5092, "kortnavn": "gb", "navn": "Grasbakke", "beskrivelse": "Grasbakke skal fremstå som en jevn og ensartet grasflate med innslag av blomstrende urter. Lavere skjøtselsnivå enn for plen og grasmark, med større toleranse for ugras og mose. Fra HB 111: \"Grasbakke skal binde sammen veg og omgivelser, samt skape grønne områder eller landskapsrom ved å framstå som en jevn og ensartet grasflate med innslag av blomstrende urter. Høyden skal være mellom 10 og 25 cm.\"", "sorteringsnummer": 3, "objektliste_dato": "2012-05-08"}], "objektliste_dato": "2012-05-08", "feltlengde": 50, "styringsparametere": {"avledet": false, "obligatorisk_verdi": false}}, {"id": 1354, "navn": "Areal", "beskrivelse": "Angir arealet av vegobjektet", "datatype": 2, "datatype_tekst": "Tall", "liste": false, "sensitivitet": 0, "sorteringsnummer": 10, "veiledning": "Kan beregnes av egengeometri (flate eller linje/kurve). Skal angis manuelt om manglende/mangelfull egengeometri", "viktighet": 3, "viktighet_tekst": "BETINGET", "sosinvdbnavn": "Areal_1354", "objektliste_dato": "2012-05-08", "min": 0, "maks": 99999, "feltlengde": 5, "enhet": {"id": 10, "navn": "Kvadratmeter", "kortnavn": "m2"}, "styringsparametere": {"avledet": false, "obligatorisk_verdi": false}}, {"id": 10493, "navn": "Sluttdato for garantitid", "beskrivelse": "Angir sluttdato for garantitid", "datatype": 8, "datatype_tekst": "Dato", "liste": false, "sensitivitet": 0, "sorteringsnummer": 44, "veiledning": "Skal kun angis for forekomster som registreres før garantitid er utløpt.", "viktighet": 3, "viktighet_tekst": "BETINGET", "sosinvdbnavn": "SluttdatoForGarantit_10493", "styringsparametere": {"avledet": false, "obligatorisk_verdi": false}}, {"id": 10303, "navn": "Anleggsår", "beskrivelse": "Angir hvilket år grasdekket ble anlagt", "datatype": 2, "datatype_tekst": "Tall", "liste": false, "sensitivitet": 0, "sorteringsnummer": 762, "viktighet": 2, "viktighet_tekst": "PÅKREVD_IKKE_ABSOLUTT", "sosinvdbnavn": "Anleggsår_10303", "objektliste_dato": "2014-11-22", "min_anbefalt": 1900, "maks_anbefalt": 2100, "min": 1800, "maks": 2100, "feltlengde": 4, "styringsparametere": {"avledet": false, "obligatorisk_verdi": false}}, {"id": 9983, "navn": "Tilleggsinformasjon", "beskrivelse": "Felt for ekstra informasjon, f.eks om det vokser andre planter inni gressarealet eller om det er satt ned løker/knoller", "datatype": 1, "datatype_tekst": "Tekst", "liste": false, "sensitivitet": 0, "sorteringsnummer": 794, "viktighet": 4, "viktighet_tekst": "OPSJONELL", "sosinvdbnavn": "Tilleggsinformasjon_9983", "feltlengde": 250, "styringsparametere": {"avledet": false, "obligatorisk_verdi": false}}, {"id": 10874, "navn": "Eier", "beskrivelse": "Angir hvem som er eier av vegobjektet.", "datatype": 30, "datatype_tekst": "FlerverdiAttributt, Tekst", "liste": false, "sensitivitet": 0, "sorteringsnummer": 902, "veiledning": "Påkrevd når grunneier avviker fra vegeier.", "viktighet": 3, "viktighet_tekst": "BETINGET", "sosinvdbnavn": "Eier_10874", "tillatte_verdier": [{"id": 17920, "kortnavn": "FK", "navn": "Fylkeskommune", "sorteringsnummer": 3}, {"id": 17921, "kortnavn": "U", "navn": "Uavklart", "beskrivelse": "Verdi benyttes inntil det er avklart hvem som er eier (ingen verdi tolkes som at vegeier er eier).", "sorteringsnummer": 8}, {"id": 18631, "kortnavn": "NV", "navn": "Stat, Nye Veier", "sorteringsnummer": 2}, {"id": 17917, "kortnavn": "SVV", "navn": "Stat, Statens vegvesen", "sorteringsnummer": 1}, {"id": 17918, "kortnavn": "K", "navn": "Kommune", "sorteringsnummer": 4}, {"id": 17919, "kortnavn": "P", "navn": "Privat", "sorteringsnummer": 6}], "feltlengde": 50, "styringsparametere": {"avledet": false, "obligatorisk_verdi": false}}, {"id": 8784, "navn": "Vedlikeholdsansvarlig", "beskrivelse": "Angir hvem som er ansvarlig for vedlikehold", "datatype": 30, "datatype_tekst": "FlerverdiAttributt, Tekst", "liste": false, "sensitivitet": 0, "sorteringsnummer": 906, "veiledning": "Påkrevd når vedlikeholdsansvarlig ikke er Statens vegvesen", "viktighet": 3, "viktighet_tekst": "BETINGET", "sosinvdbnavn": "Vedlikeholdsansvarlig_8784", "tillatte_verdier": [{"id": 17761, "kortnavn": "U", "navn": "Uavklart", "sorteringsnummer": 8}, {"id": 11624, "kortnavn": "K", "navn": "Kommune", "sorteringsnummer": 7}, {"id": 11625, "kortnavn": "P", "navn": "Privat", "sorteringsnummer": 8}, {"id": 11626, "kortnavn": "SVV", "navn": "Statens vegvesen", "sorteringsnummer": 2}, {"id": 18795, "kortnavn": "NV", "navn": "Nye Veier", "sorteringsnummer": 3}, {"id": 18924, "kortnavn": "OPS", "navn": "OPS", "sorteringsnummer": 6}], "feltlengde": 50, "styringsparametere": {"avledet": false, "obligatorisk_verdi": false}}, {"id": 11036, "navn": "Prosjektreferanse", "beskrivelse": "Referanse til prosjekt. Benyttes for å lettere kunne skille nye data fra eksisterende data i NVDB", "datatype": 1, "datatype_tekst": "Tekst", "liste": false, "sensitivitet": 0, "sorteringsnummer": 931, "viktighet": 4, "viktighet_tekst": "OPSJONELL", "sosinvdbnavn": "Prosjektreferanse_11036", "feltlengde": 200, "styringsparametere": {"avledet": false, "obligatorisk_verdi": false}}, {"id": 4723, "navn": "Geometri, linje", "beskrivelse": "Gir linje/kurve som geometrisk representerer objektet.", "datatype": 18, "datatype_tekst": "GeomLinje eller Kurve", "liste": false, "sensitivitet": 0, "sorteringsnummer": 942, "veiledning": "Grunnriss: Omriss av grasdekket. Høydereferanse: Terrenghøyde ved omriss av grasdekket", "viktighet": 2, "viktighet_tekst": "PÅKREVD_IKKE_ABSOLUTT", "sosinvdbnavn": "GeometriLinje_4723", "styringsparametere": {"avledet": false, "obligatorisk_verdi": false}}, {"id": 8911, "navn": "Geometri, flate", "beskrivelse": "Gir flate/polygon som geometrisk avgrenser området", "datatype": 19, "datatype_tekst": "GeomFlate", "liste": false, "sensitivitet": 0, "sorteringsnummer": 943, "veiledning": "Grunnriss: Omriss av grasdekket. Høydereferanse: Terrenghøyde ved omriss av grasdekket", "viktighet": 4, "viktighet_tekst": "OPSJONELL", "sosinvdbnavn": "GeometriFlate_8911", "styringsparametere": {"avledet": false, "obligatorisk_verdi": false}}, {"id": 8937, "navn": "Utgår_Geometri, punkt", "beskrivelse": "Gir punkt som geometrisk representerer objektet.", "datatype": 17, "datatype_tekst": "GeomPunkt", "liste": false, "sensitivitet": 0, "sorteringsnummer": 999, "veiledning": "Grunnriss: Omtrentlig senter av grasdekket. Høydereferanse: Terrenghøyde ved omtrentlig senter av grasdekket", "viktighet": 9, "viktighet_tekst": "HISTORISK", "sosinvdbnavn": "Utgår_GeometriPunkt_8937", "styringsparametere": {"avledet": false, "obligatorisk_verdi": false}}], "relasjonstyper": {"foreldre": [{"innenfor_mor": "JA", "relasjonstype": "KOMPOSISJON", "id": 19, "type": {"id": 49, "navn": "Trafikkøy", "objektliste_dato": "2012-05-08"}}, {"innenfor_mor": "JA", "relasjonstype": "KOMPOSISJON", "id": 21, "type": {"id": 172, "navn": "Trafikkdeler", "objektliste_dato": "2012-05-08"}}, {"relasjonstype": "AGGREGERING", "id": 592, "type": {"id": 508, "navn": "Grøntanlegg"}}], "barn": [{"innenfor_mor": "JA", "relasjonstype": "KOMPOSISJON", "id": 1688, "type": {"id": 294, "navn": "Tilstand/skade, strekning"}}, {"innenfor_mor": "JA", "relasjonstype": "KOMPOSISJON", "id": 1397, "type": {"id": 446, "navn": "Dokumentasjon"}}, {"innenfor_mor": "JA", "relasjonstype": "KOMPOSISJON", "id": 441, "type": {"id": 293, "navn": "Breddemåling"}}, {"innenfor_mor": "JA", "relasjonstype": "KOMPOSISJON", "id": 345, "type": {"id": 297, "navn": "Kommentar"}}]}, "styringsparametere": {"tidsrom_relevant": true, "sektype_20k": false, "abstrakt_type": false, "filtrering": true, "avledet": false, "må_ha_mor": false, "er_dataserie": false, "overlapp": true, "kjørefelt_relevant": "NEI", "sideposisjon_relevant": "KAN", "høyde_relevant": false, "retning_relevant": false, "flyttbar": true, "ajourhold_i": "OVERLEVER", "ajourhold_splitt": "KAN_SPLITTES", "dekningsgrad": ""}}