{"id": 291, "navn": "Viltfare", "beskrivelse": "Strekninger som er skiltet med viltfare", "stedfesting": "LINJE", "veiledning": "", "sosinvdbnavn": "Viltfare_291", "sorteringsnummer": 0, "kategorier": [{"id": 38, "name": "Alle"}, {"id": 50, "name": "Miljø - Vilt"}, {"id": 220, "name": "Kommune, standard"}, {"id": 223, "name": "Trafikkavvikling"}], "egenskapstyper": [{"id": 2221, "navn": "Art", "beskrivelse": "Angir hvilken dyreart som er antatt mest forekommende på strekningen(vises på evt skilting)", "datatype": 30, "datatype_tekst": "FlerverdiAttributt, Tekst", "liste": false, "sensitivitet": 0, "sorteringsnummer": 1, "veiledning": "Art skal normalt samsvare med skilting. Dersom det er skiltet med skiltnummer 146.3 Hjort kan det oppgis rådyr om det er kjent at det er hovedproblemet.", "viktighet": 2, "viktighet_tekst": "PÅKREVD_IKKE_ABSOLUTT", "sosinvdbnavn": "Art_2221", "tillatte_verdier": [{"id": 4072, "kortnavn": "h", "navn": "Hjort", "beskrivelse": "Hjort", "sorteringsnummer": 3}, {"id": 4073, "kortnavn": "e", "navn": "Elg", "beskrivelse": "Elg", "sorteringsnummer": 1}, {"id": 4074, "kortnavn": "r", "navn": "Rein", "beskrivelse": "Rein", "sorteringsnummer": 2}, {"id": 16783, "kortnavn": "rd", "navn": "Rådyr", "beskrivelse": "Rådyr", "sorteringsnummer": 4}], "feltlengde": 20, "styringsparametere": {"avledet": false, "obligatorisk_verdi": false}}, {"id": 10413, "navn": "Beskrivelse", "beskrivelse": "Angir øvrig intformasjon om strekning. Kan f.eks være sesongvariasjon, utdyping av hvike arter som er problem, omfang av vilt osv.", "datatype": 1, "datatype_tekst": "Tekst", "liste": false, "sensitivitet": 0, "sorteringsnummer": 2, "viktighet": 4, "viktighet_tekst": "OPSJONELL", "sosinvdbnavn": "Beskrivelse_10413", "feltlengde": 400, "styringsparametere": {"avledet": false, "obligatorisk_verdi": false}}, {"id": 10412, "navn": "Lengde", "beskrivelse": "Viltfarestrekningens lengde", "datatype": 2, "datatype_tekst": "Tall", "liste": false, "sensitivitet": 0, "sorteringsnummer": 12, "veiledning": "Angis dersom lengde avviker fra lengde av vegreferanse.", "viktighet": 3, "viktighet_tekst": "BETINGET", "sosinvdbnavn": "Lengde_10412", "standardverdi": 0.0, "min_anbefalt": 0.2, "maks_anbefalt": 100.0, "min": 0.0, "maks": 300.0, "desimaler": 1, "feltlengde": 5, "enhet": {"id": 49, "navn": "Kilometer", "kortnavn": "km"}, "styringsparametere": {"avledet": false, "obligatorisk_verdi": false}}, {"id": 8016, "navn": "Eier", "beskrivelse": "Angir hvem som er eier av vegobjektet.", "datatype": 30, "datatype_tekst": "FlerverdiAttributt, Tekst", "liste": false, "sensitivitet": 0, "sorteringsnummer": 902, "veiledning": "Påkrevd når eier avviker fra vegeier.", "viktighet": 3, "viktighet_tekst": "BETINGET", "sosinvdbnavn": "Eier_8016", "tillatte_verdier": [{"id": 18579, "kortnavn": "NV", "navn": "Stat, Nye Veier", "sorteringsnummer": 2}, {"id": 17605, "kortnavn": "U", "navn": "Uavklart", "beskrivelse": "Verdi benyttes inntil det er avklart hvem som er eier (ingen verdi tolkes som at vegeier er eier).", "sorteringsnummer": 8}, {"id": 10744, "kortnavn": "FK", "navn": "Fylkeskommune", "sorteringsnummer": 3}, {"id": 10282, "kortnavn": "SVV", "navn": "Stat, Statens vegvesen", "sorteringsnummer": 1}, {"id": 10346, "kortnavn": "K", "navn": "Kommune", "sorteringsnummer": 4}, {"id": 10410, "kortnavn": "P", "navn": "Privat", "sorteringsnummer": 6}], "feltlengde": 50, "styringsparametere": {"avledet": false, "obligatorisk_verdi": false}}, {"id": 8087, "navn": "Vedlikeholdsansvarlig", "beskrivelse": "Angir hvem som er ansvarlig for vedlikehold", "datatype": 30, "datatype_tekst": "FlerverdiAttributt, Tekst", "liste": false, "sensitivitet": 0, "sorteringsnummer": 906, "veiledning": "Påkrevd når vedlikeholdsansvarlig ikke er Statens vegvesen", "viktighet": 3, "viktighet_tekst": "BETINGET", "sosinvdbnavn": "Vedlikeholdsansvarlig_8087", "tillatte_verdier": [{"id": 10481, "kortnavn": "SVV", "navn": "Statens vegvesen", "sorteringsnummer": 2}, {"id": 18769, "kortnavn": "NV", "navn": "Nye Veier", "sorteringsnummer": 3}, {"id": 18898, "kortnavn": "OPS", "navn": "OPS", "sorteringsnummer": 6}, {"id": 17733, "kortnavn": "U", "navn": "Uavklart", "sorteringsnummer": 8}, {"id": 10637, "kortnavn": "P", "navn": "Privat", "sorteringsnummer": 8}, {"id": 10559, "kortnavn": "K", "navn": "Kommune", "sorteringsnummer": 7}], "feltlengde": 50, "styringsparametere": {"avledet": false, "obligatorisk_verdi": false}}, {"id": 11480, "navn": "Prosjektreferanse", "beskrivelse": "Referanse til prosjekt. Benyttes for å lettere kunne skille nye data fra eksisterende data i NVDB", "datatype": 1, "datatype_tekst": "Tekst", "liste": false, "sensitivitet": 0, "sorteringsnummer": 931, "viktighet": 4, "viktighet_tekst": "OPSJONELL", "sosinvdbnavn": "Prosjektreferanse_11480", "feltlengde": 200, "styringsparametere": {"avledet": false, "obligatorisk_verdi": false}}, {"id": 4890, "navn": "Geometri, linje", "beskrivelse": "Gir linje/kurve som geometrisk representerer objektet.", "datatype": 18, "datatype_tekst": "GeomLinje eller Kurve", "liste": false, "sensitivitet": 0, "sorteringsnummer": 942, "viktighet": 4, "viktighet_tekst": "OPSJONELL", "sosinvdbnavn": "GeometriLinje_4890", "styringsparametere": {"avledet": false, "obligatorisk_verdi": false}}], "relasjonstyper": {"foreldre": [], "barn": [{"innenfor_mor": "JA", "relasjonstype": "KOMPOSISJON", "id": 2096, "type": {"id": 498, "navn": "Viltskremmere/varslere"}}, {"relasjonstype": "KOMPOSISJON", "id": 2095, "type": {"id": 518, "navn": "Siktsone"}}, {"innenfor_mor": "JA", "relasjonstype": "KOMPOSISJON", "id": 2094, "type": {"id": 294, "navn": "Tilstand/skade, strekning"}}, {"innenfor_mor": "JA", "relasjonstype": "KOMPOSISJON", "id": 1500, "type": {"id": 446, "navn": "Dokumentasjon"}}, {"innenfor_mor": "JA", "relasjonstype": "KOMPOSISJON", "id": 437, "type": {"id": 297, "navn": "Kommentar"}}]}, "styringsparametere": {"tidsrom_relevant": true, "sektype_20k": false, "abstrakt_type": false, "filtrering": true, "avledet": false, "må_ha_mor": false, "er_dataserie": false, "overlapp": false, "kjørefelt_relevant": "NEI", "sideposisjon_relevant": "NEI", "høyde_relevant": false, "retning_relevant": false, "flyttbar": true, "ajourhold_i": "OVERLEVER", "ajourhold_splitt": "KAN_SPLITTES", "dekningsgrad": ""}}