{"id": 576, "navn": "Standardklasse", "beskrivelse": "Angir hvilken standardklasse vegen tilhører", "stedfesting": "LINJE", "veiledning": "", "sosinvdbnavn": "Standardklasse_576", "sorteringsnummer": 0, "kategorier": [{"id": 43, "name": "Vegnett - klassifisering"}], "egenskapstyper": [{"id": 5176, "navn": "Standardklasse", "datatype": 30, "datatype_tekst": "FlerverdiAttributt, Tekst", "liste": false, "sensitivitet": 0, "sorteringsnummer": 1, "viktighet": 0, "viktighet_tekst": "IKKE_SATT", "sosinvdbnavn": "Standardklasse_5176", "tillatte_verdier": [{"id": 7024, "kortnavn": "H1", "navn": "Hovedveg, ubebygd/spredt bebyggelse", "beskrivelse": "Hovedveg i ubebygd eller spredt bebyggelse", "sorteringsnummer": 1}, {"id": 7025, "kortnavn": "H2", "navn": "Hovedveg, middels tett bebyggelse", "beskrivelse": "Hovedveg i middels tett bebyggelse", "sorteringsnummer": 2}, {"id": 7026, "kortnavn": "H3", "navn": "Hovedveg, tett bebyggelse", "beskrivelse": "Hovedveg i tett bebyggelse", "sorteringsnummer": 3}, {"id": 7027, "kortnavn": "S1", "navn": "Samleveg, ubebygd/spredt bebyggelse", "beskrivelse": "Samleveg i ubebygd eller spredt bebyggelse", "sorteringsnummer": 5}, {"id": 7028, "kortnavn": "S2", "navn": "Samleveg, middels tett bebyggelse", "beskrivelse": "Samleveg i middels tett bebyggelse", "sorteringsnummer": 6}, {"id": 7029, "kortnavn": "S3", "navn": "Samlegate, tett bebyggelse", "beskrivelse": "Samleveg i tett bebyggelse", "sorteringsnummer": 7}, {"id": 7030, "kortnavn": "A1", "navn": "Atkomstveg, ubebygd/spredt bebyggelse", "beskrivelse": "Atkomstveg i ubebygd eller spredt bebyggelse", "sorteringsnummer": 10}, {"id": 7031, "kortnavn": "A2", "navn": "Atkomstveg, middels tett bebyggelse", "beskrivelse": "Atkomstveg i middels tett bebyggelse", "sorteringsnummer": 11}, {"id": 7032, "kortnavn": "A3", "navn": "Atkomstgate, tett bebyggelse", "beskrivelse": "Atkomstveg i tett bebyggelse", "sorteringsnummer": 12}, {"id": 7033, "kortnavn": "G/S1", "navn": "Gang-/sykkelveg, ubebygd/spredt bebyggelse", "beskrivelse": "Gang-/sykkelveg i ubebygd eller spredt bebyggelse", "sorteringsnummer": 14}, {"id": 7034, "kortnavn": "G/S2", "navn": "Gang-/sykkelveg, middels tett bebyggelse", "beskrivelse": "Gang-/sykkelveg i middels tett bebyggelse", "sorteringsnummer": 15}, {"id": 7035, "kortnavn": "G/S3", "navn": "Gang-/sykkelveg, tett bebyggelse", "beskrivelse": "Gang-/sykkelveg i tett bebyggelse", "sorteringsnummer": 16}], "feltlengde": 50, "styringsparametere": {"avledet": false, "obligatorisk_verdi": false}}, {"id": 5177, "navn": "Bebyggelsestype", "beskrivelse": "Angir hvilken type bebyggelse som er mest karakteristisk.", "datatype": 30, "datatype_tekst": "FlerverdiAttributt, Tekst", "liste": false, "sensitivitet": 0, "sorteringsnummer": 8, "viktighet": 0, "viktighet_tekst": "IKKE_SATT", "sosinvdbnavn": "Bebyggelsestype_5177", "tillatte_verdier": [{"id": 7036, "kortnavn": "b", "navn": "Bolig", "sorteringsnummer": 1}, {"id": 7037, "kortnavn": "i", "navn": "Industri", "sorteringsnummer": 2}], "feltlengde": 50, "styringsparametere": {"avledet": false, "obligatorisk_verdi": false}}, {"id": 6920, "navn": "Geometri, linje", "beskrivelse": "Gir linje/kurve som geometrisk representerer objektet.", "datatype": 18, "datatype_tekst": "GeomLinje eller Kurve", "liste": false, "sensitivitet": 0, "sorteringsnummer": 942, "viktighet": 0, "viktighet_tekst": "IKKE_SATT", "sosinvdbnavn": "GeometriLinje_6920", "styringsparametere": {"avledet": false, "obligatorisk_verdi": false}}], "relasjonstyper": {"foreldre": [], "barn": [{"innenfor_mor": "JA", "relasjonstype": "KOMPOSISJON", "id": 706, "type": {"id": 297, "navn": "Kommentar"}}]}, "styringsparametere": {"tidsrom_relevant": true, "sektype_20k": true, "abstrakt_type": false, "filtrering": true, "avledet": false, "må_ha_mor": false, "er_dataserie": false, "overlapp": false, "kjørefelt_relevant": "NEI", "sideposisjon_relevant": "NEI", "høyde_relevant": false, "retning_relevant": false, "flyttbar": true, "ajourhold_i": "OVERLEVER", "ajourhold_splitt": "KAN_IKKE_SPLITTES", "dekningsgrad": "x"}}