{"id": 624, "navn": "Fartstavle", "beskrivelse": "Tavle som viser fart til kjøretøy som passerer", "stedfesting": "PUNKT", "veiledning": "Portalens skiltpunkt legges til h.s. Enkelte portaler kan dekke hovedveg og avkjøringer ( ramper osv )", "sosinvdbnavn": "Fartstavle_624", "sorteringsnummer": 0, "kategorier": [{"id": 18, "name": "Skilt - Oppmerking - Signal"}], "egenskapstyper": [{"id": 9530, "navn": "Serienummer", "beskrivelse": "Angir serienummer på tavle", "datatype": 1, "datatype_tekst": "Tekst", "liste": false, "sensitivitet": 0, "sorteringsnummer": 9, "viktighet": 4, "viktighet_tekst": "OPSJONELL", "sosinvdbnavn": "Serienummer_9530", "feltlengde": 40, "styringsparametere": {"avledet": false, "obligatorisk_verdi": false}}, {"id": 9531, "navn": "Stasjonering", "beskrivelse": "Angir om fartstavle er mobil eller ikke", "datatype": 30, "datatype_tekst": "FlerverdiAttributt, Tekst", "liste": false, "sensitivitet": 0, "sorteringsnummer": 11, "viktighet": 2, "viktighet_tekst": "PÅKREVD_IKKE_ABSOLUTT", "sosinvdbnavn": "Stasjonering_9531", "tillatte_verdier": [{"id": 13452, "kortnavn": "F", "navn": "Fast", "sorteringsnummer": 1}, {"id": 13453, "kortnavn": "M", "navn": "Mobil", "sorteringsnummer": 2}], "feltlengde": 30, "styringsparametere": {"avledet": false, "obligatorisk_verdi": false}}, {"id": 9532, "navn": "Type måling", "beskrivelse": "Angir hvilken type fartsmåling det er benyttet.", "datatype": 30, "datatype_tekst": "FlerverdiAttributt, Tekst", "liste": false, "sensitivitet": 0, "sorteringsnummer": 16, "viktighet": 2, "viktighet_tekst": "PÅKREVD_IKKE_ABSOLUTT", "sosinvdbnavn": "TypeMåling_9532", "tillatte_verdier": [{"id": 13454, "kortnavn": "S", "navn": "Sløyfe", "sorteringsnummer": 1}, {"id": 13455, "kortnavn": "R", "navn": "Radar", "sorteringsnummer": 2}], "feltlengde": 20, "styringsparametere": {"avledet": false, "obligatorisk_verdi": false}}, {"id": 9528, "navn": "Produksjonsår", "beskrivelse": "Angir hvilket år tavla ble produsert.", "datatype": 2, "datatype_tekst": "Tall", "liste": false, "sensitivitet": 0, "sorteringsnummer": 752, "viktighet": 4, "viktighet_tekst": "OPSJONELL", "sosinvdbnavn": "Produksjonsår_9528", "min_anbefalt": 1900, "maks_anbefalt": 2050, "min": 1800, "maks": 2100, "feltlengde": 4, "styringsparametere": {"avledet": false, "obligatorisk_verdi": false}}, {"id": 10463, "navn": "Driftsmerking", "beskrivelse": "Identitet/navn på forekomst, normalt synlig på stedet", "datatype": 1, "datatype_tekst": "Tekst", "liste": false, "sensitivitet": 0, "sorteringsnummer": 792, "veiledning": "Påkrevd om merking finnes", "viktighet": 3, "viktighet_tekst": "BETINGET", "sosinvdbnavn": "Driftsmerking_10463", "feltlengde": 50, "styringsparametere": {"avledet": false, "obligatorisk_verdi": false}}, {"id": 9529, "navn": "Produktnavn", "beskrivelse": "Angir produktnavn og typebetegnelse for tavla", "datatype": 1, "datatype_tekst": "Tekst", "liste": false, "sensitivitet": 0, "sorteringsnummer": 821, "viktighet": 4, "viktighet_tekst": "OPSJONELL", "sosinvdbnavn": "Produktnavn_9529", "feltlengde": 50, "styringsparametere": {"avledet": false, "obligatorisk_verdi": false}}, {"id": 10994, "navn": "Produsentnavn", "beskrivelse": "Angir navn på produsent av vegobjektet", "datatype": 1, "datatype_tekst": "Tekst", "liste": false, "sensitivitet": 0, "sorteringsnummer": 826, "viktighet": 4, "viktighet_tekst": "OPSJONELL", "sosinvdbnavn": "Produsentnavn_10994", "feltlengde": 50, "styringsparametere": {"avledet": false, "obligatorisk_verdi": false}}, {"id": 8044, "navn": "Eier", "beskrivelse": "Angir hvem som er eier av vegobjektet.", "datatype": 30, "datatype_tekst": "FlerverdiAttributt, Tekst", "liste": false, "sensitivitet": 0, "sorteringsnummer": 902, "veiledning": "Påkrevd når eier avviker fra vegeier.", "viktighet": 3, "viktighet_tekst": "BETINGET", "sosinvdbnavn": "Eier_8044", "tillatte_verdier": [{"id": 18656, "kortnavn": "NV", "navn": "Stat, Nye Veier", "sorteringsnummer": 2}, {"id": 10771, "kortnavn": "FK", "navn": "Fylkeskommune", "sorteringsnummer": 3}, {"id": 10310, "kortnavn": "SVV", "navn": "Stat, Statens vegvesen", "sorteringsnummer": 1}, {"id": 10374, "kortnavn": "K", "navn": "Kommune", "sorteringsnummer": 4}, {"id": 10438, "kortnavn": "P", "navn": "Privat", "sorteringsnummer": 6}, {"id": 17660, "kortnavn": "U", "navn": "Uavklart", "beskrivelse": "Verdi benyttes inntil det er avklart hvem som er eier (ingen verdi tolkes som at vegeier er eier).", "sorteringsnummer": 8}], "feltlengde": 50, "styringsparametere": {"avledet": false, "obligatorisk_verdi": false}}, {"id": 8120, "navn": "Vedlikeholdsansvarlig", "beskrivelse": "Angir hvem som er ansvarlig for vedlikehold", "datatype": 30, "datatype_tekst": "FlerverdiAttributt, Tekst", "liste": false, "sensitivitet": 0, "sorteringsnummer": 906, "veiledning": "Påkrevd når vedlikeholdsansvarlig ikke er Statens vegvesen", "viktighet": 3, "viktighet_tekst": "BETINGET", "sosinvdbnavn": "Vedlikeholdsansvarlig_8120", "tillatte_verdier": [{"id": 10592, "kortnavn": "K", "navn": "Kommune", "sorteringsnummer": 7}, {"id": 10514, "kortnavn": "SVV", "navn": "Statens vegvesen", "sorteringsnummer": 2}, {"id": 18749, "kortnavn": "NV", "navn": "Nye Veier", "sorteringsnummer": 3}, {"id": 10670, "kortnavn": "P", "navn": "Privat", "sorteringsnummer": 8}, {"id": 17758, "kortnavn": "U", "navn": "Uavklart", "sorteringsnummer": 8}, {"id": 18878, "kortnavn": "OPS", "navn": "OPS", "sorteringsnummer": 6}], "feltlengde": 50, "styringsparametere": {"avledet": false, "obligatorisk_verdi": false}}, {"id": 11466, "navn": "Prosjektreferanse", "beskrivelse": "Referanse til prosjekt. Benyttes for å lettere kunne skille nye data fra eksisterende data i NVDB", "datatype": 1, "datatype_tekst": "Tekst", "liste": false, "sensitivitet": 0, "sorteringsnummer": 931, "viktighet": 4, "viktighet_tekst": "OPSJONELL", "sosinvdbnavn": "Prosjektreferanse_11466", "feltlengde": 200, "styringsparametere": {"avledet": false, "obligatorisk_verdi": false}}, {"id": 6885, "navn": "Geometri, punkt", "beskrivelse": "Gir punkt som geometrisk representerer objektet.", "datatype": 17, "datatype_tekst": "GeomPunkt", "liste": false, "sensitivitet": 0, "sorteringsnummer": 941, "veiledning": "Påkrevd for fastmonterte fartstavler. Grunnriss: Senter forkant  -  Høydereferanse: Topp tavle", "viktighet": 3, "viktighet_tekst": "BETINGET", "sosinvdbnavn": "GeometriPunkt_6885", "styringsparametere": {"avledet": false, "obligatorisk_verdi": false}}], "relasjonstyper": {"foreldre": [], "barn": [{"innenfor_mor": "JA", "relasjonstype": "KOMPOSISJON", "id": 1581, "type": {"id": 446, "navn": "Dokumentasjon"}}]}, "styringsparametere": {"tidsrom_relevant": true, "sektype_20k": false, "abstrakt_type": false, "filtrering": false, "avledet": false, "må_ha_mor": false, "er_dataserie": false, "overlapp": true, "kjørefelt_relevant": "NEI", "sideposisjon_relevant": "KAN", "høyde_relevant": false, "retning_relevant": false, "flyttbar": true, "ajourhold_i": "OVERLEVER", "ajourhold_splitt": "KAN_IKKE_SPLITTES", "dekningsgrad": ""}}