{"id": 899, "navn": "Tilstandsgrad, skjerm", "beskrivelse": "Angir tilstandsgrader for skjerm.", "stedfesting": "LINJE", "veiledning": "For testformål", "sosinvdbnavn": "TilstandsgradSkjerm_899", "sorteringsnummer": 0, "kategorier": [{"id": 226, "name": "Tilstand/skade"}], "egenskapstyper": [{"id": 10808, "navn": "TG Støy, glipper i skjerm", "beskrivelse": "Tilstandsgrad Støy, glipper i skjerm. 0=TG0, 1=TG1, 2=TG3, 3=TG3, 8=TGIU, 9=Tgmang", "datatype": 31, "datatype_tekst": "Flerverdiattributt, Tall", "liste": false, "sensitivitet": 0, "sorteringsnummer": 1, "veiledning": "For testformål", "viktighet": 4, "viktighet_tekst": "OPSJONELL", "sosinvdbnavn": "TGStøyGlipperISkjerm_10808", "tillatte_verdier": [{"id": 17793, "kortnavn": "TG1", "navn": "1", "beskrivelse": "Tilstandsgrad 1", "sorteringsnummer": 11}, {"id": 17794, "kortnavn": "TG2", "navn": "2", "beskrivelse": "Tilstandsgrad 2", "sorteringsnummer": 12}, {"id": 17795, "kortnavn": "TG3", "navn": "3", "beskrivelse": "Tilstandsgrad 3", "sorteringsnummer": 13}, {"id": 17796, "kortnavn": "TGIU", "navn": "8", "beskrivelse": "Tilstandsgrad Ikke Undersøkt", "sorteringsnummer": 18}, {"id": 17797, "kortnavn": "TGMang", "navn": "9", "beskrivelse": "Tilstandsgrad mangler", "sorteringsnummer": 19}, {"id": 17791, "kortnavn": "TG0", "navn": "0", "beskrivelse": "Tilstandsgrad 0", "sorteringsnummer": 10}], "min_anbefalt": 0, "maks_anbefalt": 9, "feltlengde": 1, "styringsparametere": {"avledet": false, "obligatorisk_verdi": false}}, {"id": 10809, "navn": "Merknad Støy, glipper i skjerm", "beskrivelse": "Merknad Støy, glipper i skjerm", "datatype": 1, "datatype_tekst": "Tekst", "liste": false, "sensitivitet": 0, "sorteringsnummer": 2, "veiledning": "For testformål", "viktighet": 4, "viktighet_tekst": "OPSJONELL", "sosinvdbnavn": "MerknadStøyGlipperIS_10809", "feltlengde": 400, "styringsparametere": {"avledet": false, "obligatorisk_verdi": false}}, {"id": 10810, "navn": "TG Støy, glipper mot terreng", "beskrivelse": "Tilstandsgrad Støy, glipper mot terreng. 0=TG0, 1=TG1, 2=TG3, 3=TG3, 8=TGIU, 9=Tgmang", "datatype": 31, "datatype_tekst": "Flerverdiattributt, Tall", "liste": false, "sensitivitet": 0, "sorteringsnummer": 3, "veiledning": "For testformål", "viktighet": 4, "viktighet_tekst": "OPSJONELL", "sosinvdbnavn": "TGStøyGlipperMotTerr_10810", "tillatte_verdier": [{"id": 17798, "kortnavn": "TG0", "navn": "0", "beskrivelse": "Tilstandsgrad 0", "sorteringsnummer": 10}, {"id": 17799, "kortnavn": "TG1", "navn": "1", "beskrivelse": "Tilstandsgrad 1", "sorteringsnummer": 11}, {"id": 17800, "kortnavn": "TG2", "navn": "2", "beskrivelse": "Tilstandsgrad 2", "sorteringsnummer": 12}, {"id": 17801, "kortnavn": "TG3", "navn": "3", "beskrivelse": "Tilstandsgrad 3", "sorteringsnummer": 13}, {"id": 17802, "kortnavn": "TGIU", "navn": "8", "beskrivelse": "Tilstandsgrad Ikke Undersøkt", "sorteringsnummer": 18}, {"id": 17803, "kortnavn": "TGMang", "navn": "9", "beskrivelse": "Tilstandsgrad mangler", "sorteringsnummer": 19}], "min_anbefalt": 0, "maks_anbefalt": 9, "feltlengde": 1, "styringsparametere": {"avledet": false, "obligatorisk_verdi": false}}, {"id": 10811, "navn": "Merknad Støy, glipper mot terreng", "beskrivelse": "Merknad Støy, glipper mot terreng", "datatype": 1, "datatype_tekst": "Tekst", "liste": false, "sensitivitet": 0, "sorteringsnummer": 4, "veiledning": "For testformål", "viktighet": 4, "viktighet_tekst": "OPSJONELL", "sosinvdbnavn": "MerknadStøyGlipperMo_10811", "feltlengde": 400, "styringsparametere": {"avledet": false, "obligatorisk_verdi": false}}, {"id": 10812, "navn": "TG Støy, absorberende elementer", "beskrivelse": "Tilstandsgrad Støy, absorberende elementer. 0=TG0, 1=TG1, 2=TG3, 3=TG3, 8=TGIU, 9=Tgmang", "datatype": 31, "datatype_tekst": "Flerverdiattributt, Tall", "liste": false, "sensitivitet": 0, "sorteringsnummer": 5, "veiledning": "For testformål", "viktighet": 4, "viktighet_tekst": "OPSJONELL", "sosinvdbnavn": "TGStøyAbsorberendeEl_10812", "tillatte_verdier": [{"id": 17808, "kortnavn": "TGIU", "navn": "8", "beskrivelse": "Tilstandsgrad Ikke Undersøkt", "sorteringsnummer": 18}, {"id": 17809, "kortnavn": "TGMang", "navn": "9", "beskrivelse": "Tilstandsgrad mangler", "sorteringsnummer": 19}, {"id": 17804, "kortnavn": "TG0", "navn": "0", "beskrivelse": "Tilstandsgrad 0", "sorteringsnummer": 10}, {"id": 17805, "kortnavn": "TG1", "navn": "1", "beskrivelse": "Tilstandsgrad 1", "sorteringsnummer": 11}, {"id": 17806, "kortnavn": "TG2", "navn": "2", "beskrivelse": "Tilstandsgrad 2", "sorteringsnummer": 12}, {"id": 17807, "kortnavn": "TG3", "navn": "3", "beskrivelse": "Tilstandsgrad 3", "sorteringsnummer": 13}], "min_anbefalt": 0, "maks_anbefalt": 9, "feltlengde": 1, "styringsparametere": {"avledet": false, "obligatorisk_verdi": false}}, {"id": 10813, "navn": "Merknad Støy, absorberende elementer", "beskrivelse": "Merknad Støy, absorberende elementer", "datatype": 1, "datatype_tekst": "Tekst", "liste": false, "sensitivitet": 0, "sorteringsnummer": 6, "veiledning": "For testformål", "viktighet": 4, "viktighet_tekst": "OPSJONELL", "sosinvdbnavn": "MerknadStøyAbsorbere_10813", "feltlengde": 400, "styringsparametere": {"avledet": false, "obligatorisk_verdi": false}}, {"id": 10814, "navn": "TG Konstruksjon, Skjevstilling", "beskrivelse": "Tilstandsgrad Konstruksjon, Skjevstilling. 0=TG0, 1=TG1, 2=TG3, 3=TG3, 8=TGIU, 9=Tgmang", "datatype": 31, "datatype_tekst": "Flerverdiattributt, Tall", "liste": false, "sensitivitet": 0, "sorteringsnummer": 7, "veiledning": "For testformål", "viktighet": 4, "viktighet_tekst": "OPSJONELL", "sosinvdbnavn": "TGKonstruksjonSkjevs_10814", "tillatte_verdier": [{"id": 17810, "kortnavn": "TG0", "navn": "0", "beskrivelse": "Tilstandsgrad 0", "sorteringsnummer": 10}, {"id": 17811, "kortnavn": "TG1", "navn": "1", "beskrivelse": "Tilstandsgrad 1", "sorteringsnummer": 11}, {"id": 17812, "kortnavn": "TG2", "navn": "2", "beskrivelse": "Tilstandsgrad 2", "sorteringsnummer": 12}, {"id": 17813, "kortnavn": "TG3", "navn": "3", "beskrivelse": "Tilstandsgrad 3", "sorteringsnummer": 13}, {"id": 17814, "kortnavn": "TGIU", "navn": "8", "beskrivelse": "Tilstandsgrad Ikke Undersøkt", "sorteringsnummer": 18}, {"id": 17815, "kortnavn": "TGMang", "navn": "9", "beskrivelse": "Tilstandsgrad mangler", "sorteringsnummer": 19}], "min_anbefalt": 0, "maks_anbefalt": 9, "feltlengde": 1, "styringsparametere": {"avledet": false, "obligatorisk_verdi": false}}, {"id": 10815, "navn": "Merknad Konstruksjon, Skjevstilling", "beskrivelse": "Merknad Konstruksjon, Skjevstilling", "datatype": 1, "datatype_tekst": "Tekst", "liste": false, "sensitivitet": 0, "sorteringsnummer": 8, "veiledning": "For testformål", "viktighet": 4, "viktighet_tekst": "OPSJONELL", "sosinvdbnavn": "MerknadKonstruksjonS_10815", "feltlengde": 400, "styringsparametere": {"avledet": false, "obligatorisk_verdi": false}}, {"id": 10816, "navn": "TG Konstruksjon, Knutepunkter/søyler", "beskrivelse": "Tilstandsgrad Konstruksjon, Knutepunkter/søyler. 0=TG0, 1=TG1, 2=TG3, 3=TG3, 8=TGIU, 9=Tgmang", "datatype": 31, "datatype_tekst": "Flerverdiattributt, Tall", "liste": false, "sensitivitet": 0, "sorteringsnummer": 9, "veiledning": "For testformål", "viktighet": 4, "viktighet_tekst": "OPSJONELL", "sosinvdbnavn": "TGKonstruksjonKnutep_10816", "tillatte_verdier": [{"id": 17816, "kortnavn": "TG0", "navn": "0", "beskrivelse": "Tilstandsgrad 0", "sorteringsnummer": 10}, {"id": 17817, "kortnavn": "TG1", "navn": "1", "beskrivelse": "Tilstandsgrad 1", "sorteringsnummer": 11}, {"id": 17818, "kortnavn": "TG2", "navn": "2", "beskrivelse": "Tilstandsgrad 2", "sorteringsnummer": 12}, {"id": 17819, "kortnavn": "TG3", "navn": "3", "beskrivelse": "Tilstandsgrad 3", "sorteringsnummer": 13}, {"id": 17820, "kortnavn": "TGIU", "navn": "8", "beskrivelse": "Tilstandsgrad Ikke Undersøkt", "sorteringsnummer": 18}, {"id": 17821, "kortnavn": "TGMang", "navn": "9", "beskrivelse": "Tilstandsgrad mangler", "sorteringsnummer": 19}], "min_anbefalt": 0, "maks_anbefalt": 9, "feltlengde": 1, "styringsparametere": {"avledet": false, "obligatorisk_verdi": false}}, {"id": 10817, "navn": "Merknad Konstruksjon, Knutepunkter/søyler", "beskrivelse": "Merknad Konstruksjon, Knutepunkter/søyler", "datatype": 1, "datatype_tekst": "Tekst", "liste": false, "sensitivitet": 0, "sorteringsnummer": 10, "veiledning": "For testformål", "viktighet": 4, "viktighet_tekst": "OPSJONELL", "sosinvdbnavn": "MerknadKonstruksjonK_10817", "feltlengde": 400, "styringsparametere": {"avledet": false, "obligatorisk_verdi": false}}, {"id": 10818, "navn": "TG Konstruksjon, Fundamenter", "beskrivelse": "Tilstandsgrad Konstruksjon, Fundamenter. 0=TG0, 1=TG1, 2=TG3, 3=TG3, 8=TGIU, 9=Tgmang", "datatype": 31, "datatype_tekst": "Flerverdiattributt, Tall", "liste": false, "sensitivitet": 0, "sorteringsnummer": 11, "veiledning": "For testformål", "viktighet": 4, "viktighet_tekst": "OPSJONELL", "sosinvdbnavn": "TGKonstruksjonFundam_10818", "tillatte_verdier": [{"id": 17824, "kortnavn": "TG2", "navn": "2", "beskrivelse": "Tilstandsgrad 2", "sorteringsnummer": 12}, {"id": 17825, "kortnavn": "TG3", "navn": "3", "beskrivelse": "Tilstandsgrad 3", "sorteringsnummer": 13}, {"id": 17826, "kortnavn": "TGIU", "navn": "8", "beskrivelse": "Tilstandsgrad Ikke Undersøkt", "sorteringsnummer": 18}, {"id": 17827, "kortnavn": "TGMang", "navn": "9", "beskrivelse": "Tilstandsgrad mangler", "sorteringsnummer": 19}, {"id": 17822, "kortnavn": "TG0", "navn": "0", "beskrivelse": "Tilstandsgrad 0", "sorteringsnummer": 10}, {"id": 17823, "kortnavn": "TG1", "navn": "1", "beskrivelse": "Tilstandsgrad 1", "sorteringsnummer": 11}], "min_anbefalt": 0, "maks_anbefalt": 9, "feltlengde": 1, "styringsparametere": {"avledet": false, "obligatorisk_verdi": false}}, {"id": 10819, "navn": "Merknad Konstruksjoner, Fundamenter", "beskrivelse": "Merknad Konstruksjoner, Fundamenter", "datatype": 1, "datatype_tekst": "Tekst", "liste": false, "sensitivitet": 0, "sorteringsnummer": 12, "veiledning": "For testformål", "viktighet": 4, "viktighet_tekst": "OPSJONELL", "sosinvdbnavn": "MerknadKonstruksjone_10819", "feltlengde": 400, "styringsparametere": {"avledet": false, "obligatorisk_verdi": false}}, {"id": 10820, "navn": "TG Konstruksjon, utvasking", "beskrivelse": "Tilstandsgrad Konstruksjon, utvasking. 0=TG0, 1=TG1, 2=TG3, 3=TG3, 8=TGIU, 9=Tgmang", "datatype": 31, "datatype_tekst": "Flerverdiattributt, Tall", "liste": false, "sensitivitet": 0, "sorteringsnummer": 13, "veiledning": "For testformål", "viktighet": 4, "viktighet_tekst": "OPSJONELL", "sosinvdbnavn": "TGKonstruksjonUtvask_10820", "tillatte_verdier": [{"id": 17828, "kortnavn": "TG0", "navn": "0", "beskrivelse": "Tilstandsgrad 0", "sorteringsnummer": 10}, {"id": 17829, "kortnavn": "TG1", "navn": "1", "beskrivelse": "Tilstandsgrad 1", "sorteringsnummer": 11}, {"id": 17830, "kortnavn": "TG2", "navn": "2", "beskrivelse": "Tilstandsgrad 2", "sorteringsnummer": 12}, {"id": 17831, "kortnavn": "TG3", "navn": "3", "beskrivelse": "Tilstandsgrad 3", "sorteringsnummer": 13}, {"id": 17832, "kortnavn": "TGIU", "navn": "8", "beskrivelse": "Tilstandsgrad Ikke Undersøkt", "sorteringsnummer": 18}, {"id": 17833, "kortnavn": "TGMang", "navn": "9", "beskrivelse": "Tilstandsgrad mangler", "sorteringsnummer": 19}], "min_anbefalt": 0, "maks_anbefalt": 9, "feltlengde": 1, "styringsparametere": {"avledet": false, "obligatorisk_verdi": false}}, {"id": 10821, "navn": "Merknad Konstruksjon, utvasking", "beskrivelse": "Merknad Konstruksjon, utvasking", "datatype": 1, "datatype_tekst": "Tekst", "liste": false, "sensitivitet": 0, "sorteringsnummer": 14, "veiledning": "For testformål", "viktighet": 4, "viktighet_tekst": "OPSJONELL", "sosinvdbnavn": "MerknadKonstruksjonU_10821", "feltlengde": 400, "styringsparametere": {"avledet": false, "obligatorisk_verdi": false}}, {"id": 10822, "navn": "TG Overflate, Tagging/hærverk etc", "beskrivelse": "Tilstandsgrad Overflate, Tagging/hærverk etc. 0=TG0, 1=TG1, 2=TG3, 3=TG3, 8=TGIU, 9=Tgmang", "datatype": 31, "datatype_tekst": "Flerverdiattributt, Tall", "liste": false, "sensitivitet": 0, "sorteringsnummer": 15, "veiledning": "For testformål", "viktighet": 4, "viktighet_tekst": "OPSJONELL", "sosinvdbnavn": "TGOverflateTaggingHæ_10822", "tillatte_verdier": [{"id": 17834, "kortnavn": "TG0", "navn": "0", "beskrivelse": "Tilstandsgrad 0", "sorteringsnummer": 10}, {"id": 17835, "kortnavn": "TG1", "navn": "1", "beskrivelse": "Tilstandsgrad 1", "sorteringsnummer": 11}, {"id": 17836, "kortnavn": "TG2", "navn": "2", "beskrivelse": "Tilstandsgrad 2", "sorteringsnummer": 12}, {"id": 17837, "kortnavn": "TG3", "navn": "3", "beskrivelse": "Tilstandsgrad 3", "sorteringsnummer": 13}, {"id": 17838, "kortnavn": "TGIU", "navn": "8", "beskrivelse": "Tilstandsgrad Ikke Undersøkt", "sorteringsnummer": 18}, {"id": 17839, "kortnavn": "TGMang", "navn": "9", "beskrivelse": "Tilstandsgrad mangler", "sorteringsnummer": 19}], "min_anbefalt": 0, "maks_anbefalt": 9, "feltlengde": 1, "styringsparametere": {"avledet": false, "obligatorisk_verdi": false}}, {"id": 10823, "navn": "Merknad Overflate, Tagging/hærverk etc", "beskrivelse": "Merknad Overflate, Tagging/hærverk etc", "datatype": 1, "datatype_tekst": "Tekst", "liste": false, "sensitivitet": 0, "sorteringsnummer": 16, "veiledning": "For testformål", "viktighet": 4, "viktighet_tekst": "OPSJONELL", "sosinvdbnavn": "MerknadOverflateTagg_10823", "feltlengde": 400, "styringsparametere": {"avledet": false, "obligatorisk_verdi": false}}, {"id": 10824, "navn": "TG Overflate, Råte/mose/sopp", "beskrivelse": "Tilstandsgrad Overflate, Råte/mose/sopp. 0=TG0, 1=TG1, 2=TG3, 3=TG3, 8=TGIU, 9=Tgmang", "datatype": 31, "datatype_tekst": "Flerverdiattributt, Tall", "liste": false, "sensitivitet": 0, "sorteringsnummer": 17, "veiledning": "For testformål", "viktighet": 4, "viktighet_tekst": "OPSJONELL", "sosinvdbnavn": "TGOverflateRåteMoseS_10824", "tillatte_verdier": [{"id": 17840, "kortnavn": "TG0", "navn": "0", "beskrivelse": "Tilstandsgrad 0", "sorteringsnummer": 10}, {"id": 17841, "kortnavn": "TG1", "navn": "1", "beskrivelse": "Tilstandsgrad 1", "sorteringsnummer": 11}, {"id": 17842, "kortnavn": "TG2", "navn": "2", "beskrivelse": "Tilstandsgrad 2", "sorteringsnummer": 12}, {"id": 17843, "kortnavn": "TG3", "navn": "3", "beskrivelse": "Tilstandsgrad 3", "sorteringsnummer": 13}, {"id": 17844, "kortnavn": "TGIU", "navn": "8", "beskrivelse": "Tilstandsgrad Ikke Undersøkt", "sorteringsnummer": 18}, {"id": 17845, "kortnavn": "TGMang", "navn": "9", "beskrivelse": "Tilstandsgrad mangler", "sorteringsnummer": 19}], "min_anbefalt": 0, "maks_anbefalt": 9, "feltlengde": 1, "styringsparametere": {"avledet": false, "obligatorisk_verdi": false}}, {"id": 10825, "navn": "Merknad Overflate, Råte/mose/sopp", "beskrivelse": "Merknad Overflate, Råte/mose/sopp", "datatype": 1, "datatype_tekst": "Tekst", "liste": false, "sensitivitet": 0, "sorteringsnummer": 18, "veiledning": "For testformål", "viktighet": 4, "viktighet_tekst": "OPSJONELL", "sosinvdbnavn": "MerknadOverflateRåte_10825", "feltlengde": 400, "styringsparametere": {"avledet": false, "obligatorisk_verdi": false}}, {"id": 10834, "navn": "TG Overflate, Vedlikehold", "beskrivelse": "Tilstandsgrad Overflate, Vedlikehold. 0=TG0, 1=TG1, 2=TG3, 3=TG3, 8=TGIU, 9=Tgmang", "datatype": 31, "datatype_tekst": "Flerverdiattributt, Tall", "liste": false, "sensitivitet": 0, "sorteringsnummer": 19, "veiledning": "For testformål", "viktighet": 4, "viktighet_tekst": "OPSJONELL", "sosinvdbnavn": "TGOverflateVedlikeho_10834", "tillatte_verdier": [{"id": 17857, "kortnavn": "TG0", "navn": "0", "beskrivelse": "Tilstandsgrad 0", "sorteringsnummer": 10}, {"id": 17858, "kortnavn": "TG1", "navn": "1", "beskrivelse": "Tilstandsgrad 1", "sorteringsnummer": 11}, {"id": 17859, "kortnavn": "TG2", "navn": "2", "beskrivelse": "Tilstandsgrad 2", "sorteringsnummer": 12}, {"id": 17860, "kortnavn": "TG3", "navn": "3", "beskrivelse": "Tilstandsgrad 3", "sorteringsnummer": 13}, {"id": 17861, "kortnavn": "TGIU", "navn": "8", "beskrivelse": "Tilstandsgrad Ikke Undersøkt", "sorteringsnummer": 18}, {"id": 17862, "kortnavn": "TGMang", "navn": "9", "beskrivelse": "Tilstandsgrad mangler", "sorteringsnummer": 19}], "min_anbefalt": 0, "maks_anbefalt": 9, "feltlengde": 1, "styringsparametere": {"avledet": false, "obligatorisk_verdi": false}}, {"id": 10835, "navn": "Merknad Overflate, Vedlikehold", "beskrivelse": "Merknad Overflate, Vedlikehold", "datatype": 1, "datatype_tekst": "Tekst", "liste": false, "sensitivitet": 0, "sorteringsnummer": 20, "veiledning": "For testformål", "viktighet": 4, "viktighet_tekst": "OPSJONELL", "sosinvdbnavn": "MerknadOverflateVedl_10835", "feltlengde": 400, "styringsparametere": {"avledet": false, "obligatorisk_verdi": false}}, {"id": 10836, "navn": "TG Samlet vurdering, støy", "beskrivelse": "Tilstandsgrad for støy som helhet.", "datatype": 31, "datatype_tekst": "Flerverdiattributt, Tall", "liste": false, "sensitivitet": 0, "sorteringsnummer": 30, "veiledning": "For testformål", "viktighet": 4, "viktighet_tekst": "OPSJONELL", "sosinvdbnavn": "TGSamletVurderingStø_10836", "tillatte_verdier": [{"id": 17872, "kortnavn": "TG3", "navn": "3", "beskrivelse": "Tilstandsgrad 3", "sorteringsnummer": 13}, {"id": 17873, "kortnavn": "TGIU", "navn": "8", "beskrivelse": "Tilstandsgrad Ikke Undersøkt", "sorteringsnummer": 18}, {"id": 17874, "kortnavn": "TGMang", "navn": "9", "beskrivelse": "Tilstandsgrad mangler", "sorteringsnummer": 19}, {"id": 17869, "kortnavn": "TG0", "navn": "0", "beskrivelse": "Tilstandsgrad 0", "sorteringsnummer": 10}, {"id": 17870, "kortnavn": "TG1", "navn": "1", "beskrivelse": "Tilstandsgrad 1", "sorteringsnummer": 11}, {"id": 17871, "kortnavn": "TG2", "navn": "2", "beskrivelse": "Tilstandsgrad 2", "sorteringsnummer": 12}], "min_anbefalt": 0, "maks_anbefalt": 9, "feltlengde": 1, "styringsparametere": {"avledet": false, "obligatorisk_verdi": false}}, {"id": 10838, "navn": "Merknad samlet vurdering, støy", "beskrivelse": "Merknad samlet vurdering, støy", "datatype": 1, "datatype_tekst": "Tekst", "liste": false, "sensitivitet": 0, "sorteringsnummer": 31, "veiledning": "For testformål", "viktighet": 4, "viktighet_tekst": "OPSJONELL", "sosinvdbnavn": "MerknadSamletVurderi_10838", "feltlengde": 400, "styringsparametere": {"avledet": false, "obligatorisk_verdi": false}}, {"id": 10837, "navn": "TG Samlet vurdering, konstruksjon", "beskrivelse": "Tilstandsgrad for konstruksjon som helhet.", "datatype": 31, "datatype_tekst": "Flerverdiattributt, Tall", "liste": false, "sensitivitet": 0, "sorteringsnummer": 32, "veiledning": "For testformål", "viktighet": 4, "viktighet_tekst": "OPSJONELL", "sosinvdbnavn": "TGSamletVurderingKon_10837", "tillatte_verdier": [{"id": 17863, "kortnavn": "TG0", "navn": "0", "beskrivelse": "Tilstandsgrad 0", "sorteringsnummer": 10}, {"id": 17864, "kortnavn": "TG1", "navn": "1", "beskrivelse": "Tilstandsgrad 1", "sorteringsnummer": 11}, {"id": 17865, "kortnavn": "TG2", "navn": "2", "beskrivelse": "Tilstandsgrad 2", "sorteringsnummer": 12}, {"id": 17866, "kortnavn": "TG3", "navn": "3", "beskrivelse": "Tilstandsgrad 3", "sorteringsnummer": 13}, {"id": 17867, "kortnavn": "TGIU", "navn": "8", "beskrivelse": "Tilstandsgrad Ikke Undersøkt", "sorteringsnummer": 18}, {"id": 17868, "kortnavn": "TGMang", "navn": "9", "beskrivelse": "Tilstandsgrad mangler", "sorteringsnummer": 19}], "min_anbefalt": 0, "maks_anbefalt": 9, "feltlengde": 1, "styringsparametere": {"avledet": false, "obligatorisk_verdi": false}}, {"id": 10839, "navn": "Merknad samlet vurdering, konstruksjon", "beskrivelse": "Merknad samlet vurdering, konstruksjon", "datatype": 1, "datatype_tekst": "Tekst", "liste": false, "sensitivitet": 0, "sorteringsnummer": 33, "veiledning": "For testformål", "viktighet": 4, "viktighet_tekst": "OPSJONELL", "sosinvdbnavn": "MerknadSamletVurderi_10839", "feltlengde": 400, "styringsparametere": {"avledet": false, "obligatorisk_verdi": false}}, {"id": 10826, "navn": "TG Samlet vurdering", "beskrivelse": "Tilstandsgrad for skjerm som helhet", "datatype": 31, "datatype_tekst": "Flerverdiattributt, Tall", "liste": false, "sensitivitet": 0, "sorteringsnummer": 34, "veiledning": "For testformål", "viktighet": 4, "viktighet_tekst": "OPSJONELL", "sosinvdbnavn": "TGSamletVurdering_10826", "tillatte_verdier": [{"id": 17850, "kortnavn": "TG0", "navn": "0", "beskrivelse": "Tilstandsgrad 0", "sorteringsnummer": 10}, {"id": 17851, "kortnavn": "TG1", "navn": "1", "beskrivelse": "Tilstandsgrad 1", "sorteringsnummer": 11}, {"id": 17852, "kortnavn": "TG2", "navn": "2", "beskrivelse": "Tilstandsgrad 2", "sorteringsnummer": 12}, {"id": 17853, "kortnavn": "TG3", "navn": "3", "beskrivelse": "Tilstandsgrad 3", "sorteringsnummer": 13}, {"id": 17854, "kortnavn": "TGIU", "navn": "8", "beskrivelse": "Tilstandsgrad Ikke Undersøkt", "sorteringsnummer": 18}, {"id": 17855, "kortnavn": "TGMang", "navn": "9", "beskrivelse": "Tilstandsgrad mangler", "sorteringsnummer": 19}], "min_anbefalt": 0, "maks_anbefalt": 9, "feltlengde": 1, "styringsparametere": {"avledet": false, "obligatorisk_verdi": false}}, {"id": 10827, "navn": "Merknad samlet vurdering", "beskrivelse": "Merknad samlet vurdering", "datatype": 1, "datatype_tekst": "Tekst", "liste": false, "sensitivitet": 0, "sorteringsnummer": 35, "veiledning": "For testformål", "viktighet": 4, "viktighet_tekst": "OPSJONELL", "sosinvdbnavn": "MerknadSamletVurderi_10827", "feltlengde": 400, "styringsparametere": {"avledet": false, "obligatorisk_verdi": false}}, {"id": 10828, "navn": "Registreringsdato", "beskrivelse": "Registreringsdato", "datatype": 8, "datatype_tekst": "Dato", "liste": false, "sensitivitet": 0, "sorteringsnummer": 50, "veiledning": "For testformål", "viktighet": 4, "viktighet_tekst": "OPSJONELL", "sosinvdbnavn": "Registreringsdato_10828", "styringsparametere": {"avledet": false, "obligatorisk_verdi": false}}, {"id": 10829, "navn": "Signatur", "beskrivelse": "Signatur", "datatype": 1, "datatype_tekst": "Tekst", "liste": false, "sensitivitet": 0, "sorteringsnummer": 51, "veiledning": "For testformål", "viktighet": 4, "viktighet_tekst": "OPSJONELL", "sosinvdbnavn": "Signatur_10829", "feltlengde": 30, "styringsparametere": {"avledet": false, "obligatorisk_verdi": false}}, {"id": 10830, "navn": "Geometri, linje", "beskrivelse": "Gir linje/kurve som geometrisk representerer objektet.", "datatype": 18, "datatype_tekst": "GeomLinje eller Kurve", "liste": false, "sensitivitet": 0, "sorteringsnummer": 942, "veiledning": "For testformål", "viktighet": 4, "viktighet_tekst": "OPSJONELL", "sosinvdbnavn": "GeometriLinje_10830", "styringsparametere": {"avledet": false, "obligatorisk_verdi": false}}], "relasjonstyper": {"foreldre": [{"relasjonstype": "KOMPOSISJON", "id": 2133, "type": {"id": 3, "navn": "Skjerm"}}], "barn": [{"relasjonstype": "KOMPOSISJON", "id": 2134, "type": {"id": 446, "navn": "Dokumentasjon"}}]}, "styringsparametere": {"tidsrom_relevant": false, "sektype_20k": false, "abstrakt_type": false, "filtrering": true, "avledet": false, "må_ha_mor": false, "er_dataserie": false, "overlapp": true, "kjørefelt_relevant": "NEI", "sideposisjon_relevant": "KAN", "høyde_relevant": false, "retning_relevant": false, "flyttbar": true, "ajourhold_i": "IKKE_TATT_STILLING", "ajourhold_splitt": "IKKE_TATT_STILLING", "dekningsgrad": ""}}