{"id": 906, "navn": "Elektrisk komponent (test)", "beskrivelse": "Enkelt teknisk/elektrisk komponent, som f.eks. sikring, jordfeilautomat eller kommunikasjonsutstyr", "stedfesting": "PUNKT", "veiledning": "", "sosinvdbnavn": "ElektriskKomponent_tes_906", "sorteringsnummer": 0, "kategorier": [{"id": 12, "name": "Belysning - Elektro"}], "egenskapstyper": [{"id": 10938, "navn": "Type", "beskrivelse": "Angir hvilken type det er tale om", "datatype": 30, "datatype_tekst": "FlerverdiAttributt, Tekst", "liste": false, "sensitivitet": 0, "sorteringsnummer": 1, "viktighet": 2, "viktighet_tekst": "PÅKREVD_IKKE_ABSOLUTT", "sosinvdbnavn": "Type_10938", "tillatte_verdier": [{"id": 18279, "kortnavn": "B", "navn": "Bryter", "sorteringsnummer": 1}, {"id": 18280, "kortnavn": "S", "navn": "Sikring", "beskrivelse": "Ulike typer sikring. Inkludert automatasikring", "sorteringsnummer": 2}, {"id": 18281, "kortnavn": "J", "navn": "Jordfeilbryter", "sorteringsnummer": 3}, {"id": 18282, "kortnavn": "J", "navn": "Rele/Kontraktor", "sorteringsnummer": 4}, {"id": 18283, "kortnavn": "J", "navn": "Strømforsyning", "sorteringsnummer": 5}, {"id": 18284, "kortnavn": "J", "navn": "Stikkontakt", "sorteringsnummer": 6}, {"id": 18285, "kortnavn": "J", "navn": "Rekkeklemme", "sorteringsnummer": 7}, {"id": 18286, "kortnavn": "J", "navn": "Varme", "sorteringsnummer": 8}], "feltlengde": 40, "styringsparametere": {"avledet": false, "obligatorisk_verdi": false}}, {"id": 11447, "navn": "Byggeår", "beskrivelse": "Angir byggeår.", "datatype": 2, "datatype_tekst": "Tall", "liste": false, "sensitivitet": 0, "sorteringsnummer": 3, "viktighet": 2, "viktighet_tekst": "PÅKREVD_IKKE_ABSOLUTT", "sosinvdbnavn": "Byggeår_11447", "feltlengde": 4, "styringsparametere": {"avledet": false, "obligatorisk_verdi": false}}, {"id": 10939, "navn": "Tilleggsinformasjon", "beskrivelse": "Mulighet for å beskrive ytterligere detaljer om komponenten", "datatype": 1, "datatype_tekst": "Tekst", "liste": false, "sensitivitet": 0, "sorteringsnummer": 794, "viktighet": 4, "viktighet_tekst": "OPSJONELL", "sosinvdbnavn": "Tilleggsinformasjon_10939", "feltlengde": 400, "styringsparametere": {"avledet": false, "obligatorisk_verdi": false}}, {"id": 10936, "navn": "Produktnavn", "beskrivelse": "Gir produktnavn, modellbetegnelse mm i form av navn og eller nummer", "datatype": 1, "datatype_tekst": "Tekst", "liste": false, "sensitivitet": 0, "sorteringsnummer": 821, "viktighet": 4, "viktighet_tekst": "OPSJONELL", "sosinvdbnavn": "Produktnavn_10936", "feltlengde": 200, "styringsparametere": {"avledet": false, "obligatorisk_verdi": false}}, {"id": 10935, "navn": "Produsentnavn", "beskrivelse": "Angir merke/produsentnavn/fabrikant", "datatype": 1, "datatype_tekst": "Tekst", "liste": false, "sensitivitet": 0, "sorteringsnummer": 826, "viktighet": 4, "viktighet_tekst": "OPSJONELL", "sosinvdbnavn": "Produsentnavn_10935", "feltlengde": 100, "styringsparametere": {"avledet": false, "obligatorisk_verdi": false}}, {"id": 10937, "navn": "Geometri, punkt", "beskrivelse": "Gir punkt som geometrisk representerer objektet.", "datatype": 17, "datatype_tekst": "GeomPunkt", "liste": false, "sensitivitet": 0, "sorteringsnummer": 941, "viktighet": 4, "viktighet_tekst": "OPSJONELL", "sosinvdbnavn": "GeometriPunkt_10937", "styringsparametere": {"avledet": false, "obligatorisk_verdi": false}}], "relasjonstyper": {"foreldre": [{"relasjonstype": "KOMPOSISJON", "id": 2142, "type": {"id": 65, "navn": "Bygning"}}, {"relasjonstype": "KOMPOSISJON", "id": 2141, "type": {"id": 819, "navn": "Fordelingstavle"}}], "barn": []}, "styringsparametere": {"tidsrom_relevant": true, "sektype_20k": false, "abstrakt_type": false, "filtrering": false, "avledet": false, "må_ha_mor": true, "er_dataserie": false, "overlapp": true, "kjørefelt_relevant": "KAN", "sideposisjon_relevant": "KAN", "høyde_relevant": false, "retning_relevant": false, "flyttbar": true, "ajourhold_i": "OVERLEVER", "ajourhold_splitt": "KAN_IKKE_SPLITTES", "dekningsgrad": ""}}